onchains/__init__.py
onchains/api.py
onchains-0.0.1.dist-info/METADATA
onchains-0.0.1.dist-info/WHEEL
onchains-0.0.1.dist-info/top_level.txt
onchains-0.0.1.dist-info/RECORD
